simple_timebox-0.1.post1.data/scripts/app.py
timebox/__init__.py
timebox/app.py
timebox/lib/__init__.py
timebox/lib/hue.py
timebox/lib/sound.py
timebox/lib/support.py
simple_timebox-0.1.post1.dist-info/LICENSE.md
simple_timebox-0.1.post1.dist-info/METADATA
simple_timebox-0.1.post1.dist-info/WHEEL
simple_timebox-0.1.post1.dist-info/entry_points.txt
simple_timebox-0.1.post1.dist-info/top_level.txt
simple_timebox-0.1.post1.dist-info/RECORD
