Metadata-Version: 2.1
Name: simple-timebox
Version: 0.1.post1
Summary: A simple countdown timer to boost effectiveness.
Home-page: https://github.com/stigoleg/Timebox
Author: Stig-Ole Gundersen
Author-email: stigole.gundersen@gmail.com
License: MIT
Keywords: timebox,time,time management technique
Platform: UNKNOWN
Classifier: Development Status :: 5 - Production/Stable
Classifier: Intended Audience :: Information Technology
Classifier: License :: OSI Approved :: MIT License
Classifier: Programming Language :: Python :: 3.5
Classifier: Programming Language :: Python :: 3.6
Classifier: Programming Language :: Python :: 3.7
Requires-Dist: click (==7.0)
Requires-Dist: numpy (==1.17.3)
Requires-Dist: simpleaudio (==1.0.2)
